bin/ndmetis
bin/cmpfillin
bin/m2gmetis
bin/mpmetis
bin/graphchk
bin/gpmetis
include/metis.h
sksparse_minimal/__init__.py
sksparse_minimal/main_test.py
sksparse_minimal/_cholespy_core.cpython-39-darwin.so
sksparse_minimal/main.py
sksparse_minimal-0.2.dist-info/RECORD
sksparse_minimal-0.2.dist-info/WHEEL
sksparse_minimal-0.2.dist-info/entry_points.txt
sksparse_minimal-0.2.dist-info/METADATA
sksparse_minimal-0.2.dist-info/licenses/LICENSE
lib/libmetis.a
