Metadata-Version: 2.1
Name: sksparse-minimal
Version: 0.2
Summary: A drop in replacement for sksparse for sparse Cholseky factorization
Keywords: cholesky sksparse
Author-Email: Jeff Quinn <quinnj2@mskcc.org>
Maintainer-Email: Jeff Quinn <quinnj2@mskcc.org>
Project-URL: Homepage, https://github.com/tansey-lab/sksparse_minimal
Project-URL: Bug tracker, https://github.com/tansey-lab/sksparse_minimal/issues
Requires-Python: >=3.8
Requires-Dist: numpy
Requires-Dist: scipy
Requires-Dist: check-manifest; extra == "dev"
Requires-Dist: pytest; extra == "test"
Requires-Dist: tox; extra == "test"
Provides-Extra: dev
Provides-Extra: test
